pstatstools/__init__.py
pstatstools/categorical.py
pstatstools/distributions.py
pstatstools/error_propagation.py
pstatstools/inferential.py
pstatstools/nonparametric.py
pstatstools/probability.py
pstatstools/samples.py
pstatstools-0.0.12.dist-info/licenses/LICENSE
pstatstools-0.0.12.dist-info/METADATA
pstatstools-0.0.12.dist-info/WHEEL
pstatstools-0.0.12.dist-info/top_level.txt
pstatstools-0.0.12.dist-info/RECORD
