Metadata-Version: 2.4
Name: pstatstools
Version: 0.0.12
Summary: Statistical tools package
License: MIT
Classifier: Programming Language :: Python :: 3
Classifier: License :: OSI Approved :: MIT License
Classifier: Operating System :: OS Independent
Requires-Python: >=3.6
License-File: LICENSE
Requires-Dist: numpy>=1.19.0
Requires-Dist: scipy>=1.7.0
Requires-Dist: matplotlib>=3.4.0
Requires-Dist: statsmodels>=0.13.0
Requires-Dist: pandas>=1.3.0
Requires-Dist: jinja2>=3.0.0
Dynamic: license-file
Dynamic: requires-python
